csv2bufr/__init__.py
csv2bufr/cli.py
csv2bufr/pygeoapi_plugin.py
csv2bufr/templates/__init__.py
csv2bufr/templates/resources/schema/csv2bufr-template-v2.json
csv2bufr/templates/resources/schema/csv2bufr-template-v3.json
csv2bufr-0.8.7.dist-info/LICENSE
csv2bufr-0.8.7.dist-info/METADATA
csv2bufr-0.8.7.dist-info/WHEEL
csv2bufr-0.8.7.dist-info/entry_points.txt
csv2bufr-0.8.7.dist-info/top_level.txt
csv2bufr-0.8.7.dist-info/RECORD
